pyenerginetpowerrightnow/__init__.py
pyenerginetpowerrightnow-22.2.1.dist-info/METADATA
pyenerginetpowerrightnow-22.2.1.dist-info/WHEEL
pyenerginetpowerrightnow-22.2.1.dist-info/licenses/LICENSE
pyenerginetpowerrightnow-22.2.1.dist-info/RECORD
