Metadata-Version: 2.1
Name: pyenerginetpowerrightnow
Version: 22.2.1
Summary: A small python library to access electrical energy statistics for Denmark
Project-URL: Homepage, https://gitlab.com/m6cx1/pyenerginetpowerrightnow
Project-URL: Bug Tracker, https://gitlab.com/m6cx1/pyenerginetpowerrightnow/-/issues
Author-email: Thilo Bangert <thilo.bangert@gmail.com>
License-File: LICENSE
Classifier: License :: OSI Approved :: MIT License
Classifier: Operating System :: OS Independent
Classifier: Programming Language :: Python :: 3
Requires-Python: >=3.7
